optimum_transformers/__init__.py
optimum_transformers/generation_utils.py
optimum_transformers/benchmark/__init__.py
optimum_transformers/benchmark/base.py
optimum_transformers/pipelines/__init__.py
optimum_transformers/pipelines/base.py
optimum_transformers/pipelines/feature_extraction.py
optimum_transformers/pipelines/fill_mask.py
optimum_transformers/pipelines/question_answering.py
optimum_transformers/pipelines/text_classification.py
optimum_transformers/pipelines/text_generation.py
optimum_transformers/pipelines/token_classification.py
optimum_transformers/pipelines/zero_shot_classification.py
optimum_transformers/utils/__init__.py
optimum_transformers/utils/benchmark.py
optimum_transformers/utils/testing.py
tests/__init__.py
tests/pipelines/__init__.py
tests/pipelines/test_pipelines_common.py
tests/pipelines/test_pipelines_question_answering.py
tests/pipelines/test_pipelines_token_classification.py
tests/pipelines/test_pipelines_zero_shot.py
optimum_transformers-0.2.1.dist-info/LICENSE
optimum_transformers-0.2.1.dist-info/METADATA
optimum_transformers-0.2.1.dist-info/WHEEL
optimum_transformers-0.2.1.dist-info/top_level.txt
optimum_transformers-0.2.1.dist-info/RECORD
