Metadata-Version: 2.1
Name: optimum-transformers
Version: 0.2.1
Summary: Accelerated nlp pipelines using Transformers, Optimum and ONNX Runtime
Home-page: https://github.com/AlekseyKorshuk/optimum-transformers
Author: Aleksey Korshuk
Author-email: ale-kor02@mail.ru
License: Apache
Project-URL: Documentation, https://github.com/AlekseyKorshuk/optimum-transformers
Project-URL: Source, https://github.com/AlekseyKorshuk/optimum-transformers
Keywords: ONNX,onnxruntime,NLP,transformer,transformers,inference,fast inference,Optimum,infinity
Platform: UNKNOWN
Classifier: Development Status :: 3 - Alpha
Classifier: Intended Audience :: Developers
Classifier: License :: OSI Approved :: Apache Software License
Classifier: Operating System :: OS Independent
Classifier: Programming Language :: Python :: 3
Classifier: Programming Language :: Python :: 3.6
Classifier: Programming Language :: Python :: 3.7
Classifier: Topic :: Scientific/Engineering :: Artificial Intelligence
Requires-Python: >=3.6.0
License-File: LICENSE
Requires-Dist: coloredlogs (<16.0,>=15.0)
Requires-Dist: datasets (<3.0,>=2.0)
Requires-Dist: matplotlib (<4.0,>=3.5)
Requires-Dist: onnx (<2.0,>=1.10)
Requires-Dist: onnxruntime (==1.10)
Requires-Dist: optimum (==1.0.0)
Requires-Dist: psutil (<6.0,>=5.9)
Requires-Dist: seaborn (<1.0,>=0.11)
Requires-Dist: transformers (<5.0,>=4.15)
Requires-Dist: tokenizers (<0.12,>=0.11.6)
Requires-Dist: sentencepiece (<0.2,>=0.1.96)
Provides-Extra: dev
Requires-Dist: pytest ; extra == 'dev'
Requires-Dist: pytest-xdist ; extra == 'dev'
Requires-Dist: timeout-decorator ; extra == 'dev'
Requires-Dist: psutil ; extra == 'dev'
Requires-Dist: black (>=20.8b1) ; extra == 'dev'
Requires-Dist: isort (>=5) ; extra == 'dev'
Requires-Dist: flake8 ; extra == 'dev'
Provides-Extra: quality
Requires-Dist: black (>=20.8b1) ; extra == 'quality'
Requires-Dist: isort (>=5) ; extra == 'quality'
Requires-Dist: flake8 ; extra == 'quality'
Provides-Extra: testing
Requires-Dist: pytest ; extra == 'testing'
Requires-Dist: pytest-xdist ; extra == 'testing'
Requires-Dist: timeout-decorator ; extra == 'testing'
Requires-Dist: psutil ; extra == 'testing'
